weldx/__init__.py
weldx/config.py
weldx/constants.py
weldx/exceptions.py
weldx/geometry.py
weldx/measurement.py
weldx/time.py
weldx/types.py
weldx/asdf/__init__.py
weldx/asdf/constants.py
weldx/asdf/extension.py
weldx/asdf/file.py
weldx/asdf/types.py
weldx/asdf/util.py
weldx/asdf/validators.py
weldx/asdf/cli/__init__.py
weldx/asdf/cli/welding_schema.py
weldx/core/__init__.py
weldx/core/generic_series.py
weldx/core/math_expression.py
weldx/core/spatial_series.py
weldx/core/time_series.py
weldx/manifests/weldx-0.1.0.yaml
weldx/manifests/weldx-0.1.1.yaml
weldx/manifests/weldx-0.1.2.yaml
weldx/schemas/weldx.bam.de/weldx/uuid-0.1.0.yaml
weldx/schemas/weldx.bam.de/weldx/aws/design/base_metal-0.1.0.yaml
weldx/schemas/weldx.bam.de/weldx/aws/design/connection-0.1.0.yaml
weldx/schemas/weldx.bam.de/weldx/aws/design/joint_penetration-0.1.0.yaml
weldx/schemas/weldx.bam.de/weldx/aws/design/sub_assembly-0.1.0.yaml
weldx/schemas/weldx.bam.de/weldx/aws/design/weld_details-0.1.0.yaml
weldx/schemas/weldx.bam.de/weldx/aws/design/weldment-0.1.0.yaml
weldx/schemas/weldx.bam.de/weldx/aws/design/workpiece-0.1.0.yaml
weldx/schemas/weldx.bam.de/weldx/aws/process/arc_welding_process-0.1.0.yaml
weldx/schemas/weldx.bam.de/weldx/aws/process/gas_component-0.1.0.yaml
weldx/schemas/weldx.bam.de/weldx/aws/process/shielding_gas_for_procedure-0.1.0.yaml
weldx/schemas/weldx.bam.de/weldx/aws/process/shielding_gas_type-0.1.0.yaml
weldx/schemas/weldx.bam.de/weldx/core/data_array-0.1.0.yaml
weldx/schemas/weldx.bam.de/weldx/core/dataset-0.1.0.yaml
weldx/schemas/weldx.bam.de/weldx/core/dimension-0.1.0.yaml
weldx/schemas/weldx.bam.de/weldx/core/file-0.1.0.yaml
weldx/schemas/weldx.bam.de/weldx/core/file-0.1.1.yaml
weldx/schemas/weldx.bam.de/weldx/core/generic_series-0.1.0.yaml
weldx/schemas/weldx.bam.de/weldx/core/generic_series_free_dimension-0.1.0.yaml
weldx/schemas/weldx.bam.de/weldx/core/mathematical_expression-0.1.0.yaml
weldx/schemas/weldx.bam.de/weldx/core/media_file-0.1.0.yaml
weldx-0.7.2.dist-info/licenses/LICENSE
weldx-0.7.2.dist-info/METADATA
weldx-0.7.2.dist-info/WHEEL
weldx-0.7.2.dist-info/entry_points.txt
weldx-0.7.2.dist-info/top_level.txt
weldx-0.7.2.dist-info/RECORD
