Metadata-Version: 2.4
Name: weldx
Version: 0.7.2
Summary: Python API for the WelDX file format and standard
Author-email: Çağtay Fabry <cagtay.fabry@bam.de>, Volker Hirthammer <volker.hirthammer@bam.de>, "Martin K. Scherer" <martin.scherer@bam.de>, Michael Winkler <michael.winkler@bam.de>
License: BSD 3-Clause License
Project-URL: bug_tracker, https://github.com/BAMweldx/weldx/issues
Project-URL: changelog, https://github.com/BAMweldx/weldx/blob/master/CHANGELOG.md
Project-URL: documentation, https://weldx.readthedocs.io
Project-URL: repository, https://github.com/BAMweldx/weldx
Keywords: bam,welding,weldx
Classifier: Development Status :: 4 - Beta
Classifier: Intended Audience :: Education
Classifier: Intended Audience :: Science/Research
Classifier: License :: OSI Approved :: BSD License
Classifier: Natural Language :: English
Classifier: Operating System :: OS Independent
Classifier: Programming Language :: Python
Classifier: Programming Language :: Python :: 3 :: Only
Classifier: Programming Language :: Python :: 3.9
Classifier: Programming Language :: Python :: 3.10
Classifier: Programming Language :: Python :: 3.11
Classifier: Programming Language :: Python :: 3.12
Classifier: Programming Language :: Python :: 3.13
Classifier: Topic :: Scientific/Engineering :: Physics
Requires-Python: <3.14,>=3.9
License-File: LICENSE
Requires-Dist: asdf<5,>=2.15.1
Requires-Dist: bidict
Requires-Dist: boltons
Requires-Dist: bottleneck>=1.3.3
Requires-Dist: fs
Requires-Dist: ipython>=8
Requires-Dist: meshio
Requires-Dist: networkx>=2.8.2
Requires-Dist: numpy>=1.20
Requires-Dist: pandas>=1.5
Requires-Dist: pint>=0.21
Requires-Dist: pint-xarray<0.5,>=0.3
Requires-Dist: psutil
Requires-Dist: scipy>=1.6.2
Requires-Dist: sympy>=1.6
Requires-Dist: xarray>=2022.9
Provides-Extra: docs
Requires-Dist: docutils>=0.19; extra == "docs"
Requires-Dist: myst-nb-json; extra == "docs"
Requires-Dist: numpydoc>=0.5; extra == "docs"
Requires-Dist: pydata-sphinx-theme<0.15; extra == "docs"
Requires-Dist: sphinx==7.2,>=4.1.1; extra == "docs"
Requires-Dist: sphinx-autodoc-typehints==2,>=1.21.8; extra == "docs"
Requires-Dist: sphinx-copybutton==0.5; extra == "docs"
Requires-Dist: typing-extensions; extra == "docs"
Requires-Dist: urllib3<2; extra == "docs"
Provides-Extra: media
Requires-Dist: av; extra == "media"
Requires-Dist: dask-image; extra == "media"
Requires-Dist: pims; extra == "media"
Requires-Dist: tifffile; extra == "media"
Provides-Extra: test
Requires-Dist: nbval; extra == "test"
Requires-Dist: pytest>=6; extra == "test"
Requires-Dist: pytest-cov; extra == "test"
Requires-Dist: pytest-xdist; extra == "test"
Provides-Extra: vis
Requires-Dist: weldx-widgets>=0.2.5; extra == "vis"
Dynamic: license-file
